bsm/BSMCLI_CMD
bsm/VERSION
bsm/__init__.py
bsm/cli.py
bsm/const.py
bsm/env.py
bsm/git.py
bsm/loader.py
bsm/logger.py
bsm/cmd/__init__.py
bsm/cmd/clean.py
bsm/cmd/config.py
bsm/cmd/current.py
bsm/cmd/default.py
bsm/cmd/exit.py
bsm/cmd/home.py
bsm/cmd/init.py
bsm/cmd/install.py
bsm/cmd/ls.py
bsm/cmd/ls_env.py
bsm/cmd/ls_remote.py
bsm/cmd/pack.py
bsm/cmd/pkg_base.py
bsm/cmd/pkg_build.py
bsm/cmd/pkg_clean.py
bsm/cmd/pkg_config.py
bsm/cmd/pkg_edit.py
bsm/cmd/pkg_init.py
bsm/cmd/pkg_install.py
bsm/cmd/pkg_ls.py
bsm/cmd/pkg_path.py
bsm/cmd/pkg_remove.py
bsm/cmd/pkg_use.py
bsm/cmd/refresh.py
bsm/cmd/run.py
bsm/cmd/setup.py
bsm/cmd/upgrade.py
bsm/cmd/use.py
bsm/cmd/version.py
bsm/cmd/output/__init__.py
bsm/cmd/output/json.py
bsm/cmd/output/plain.py
bsm/cmd/output/python.py
bsm/cmd/output/yaml.py
bsm/config/__init__.py
bsm/config/app.py
bsm/config/category.py
bsm/config/category_priority.py
bsm/config/common_dict.py
bsm/config/common_list.py
bsm/config/env.py
bsm/config/option.py
bsm/config/package_base.py
bsm/config/package_check.py
bsm/config/package_install.py
bsm/config/package_path.py
bsm/config/package_runtime.py
bsm/config/release.py
bsm/config/release_install.py
bsm/config/release_origin.py
bsm/config/release_path.py
bsm/config/scenario.py
bsm/config/util/__init__.py
bsm/handler/__init__.py
bsm/handler/version_compare.py
bsm/handler/install/__init__.py
bsm/handler/install/command.py
bsm/handler/install/empty.py
bsm/operation/__init__.py
bsm/operation/build_package.py
bsm/operation/check_conflict_package.py
bsm/operation/check_missing.py
bsm/operation/clean.py
bsm/operation/clean_package.py
bsm/operation/create_package_config.py
bsm/operation/detect_category.py
bsm/operation/detect_package.py
bsm/operation/detect_package_param.py
bsm/operation/exit.py
bsm/operation/find_package.py
bsm/operation/install_package.py
bsm/operation/install_package_config.py
bsm/operation/install_release.py
bsm/operation/install_release_packages.py
bsm/operation/load_package.py
bsm-1.0.0a1.dist-info/LICENSE
bsm-1.0.0a1.dist-info/METADATA
bsm-1.0.0a1.dist-info/WHEEL
bsm-1.0.0a1.dist-info/entry_points.txt
bsm-1.0.0a1.dist-info/top_level.txt
bsm-1.0.0a1.dist-info/RECORD
