Metadata-Version: 2.1
Name: bsm
Version: 1.0.0a1
Summary: Bundled software manager
Home-page: https://github.com/bsmhep/bsm
Author: Xianghu Zhao
Author-email: xianghuzhao@gmail.com
License: MIT
Keywords: bsm
Platform: UNKNOWN
Classifier: Development Status :: 5 - Production/Stable
Classifier: Intended Audience :: Science/Research
Classifier: Topic :: Scientific/Engineering :: Physics
Classifier: Topic :: System :: Software Distribution
Classifier: License :: OSI Approved :: MIT License
Classifier: Programming Language :: Python :: 2
Classifier: Programming Language :: Python :: 2.7
Classifier: Programming Language :: Python :: 3
Classifier: Programming Language :: Python :: 3.3
Classifier: Programming Language :: Python :: 3.4
Classifier: Programming Language :: Python :: 3.5
Classifier: Programming Language :: Python :: 3.6
Classifier: Programming Language :: Python :: 3.7
Classifier: Programming Language :: Python :: Implementation :: CPython
Classifier: Programming Language :: Python :: Implementation :: PyPy
Requires-Dist: click
Requires-Dist: PyYAML
Requires-Dist: packaging
